{
    "packages": {
        "phpclasses/anagrams": [
            {
                "name": "phpclasses/anagrams",
                "version": "1.0.0",
                "version_normalized": "1.0.0.0",
                "dist": {
                    "type": "zip",
                    "url": "https://www.phpclasses.org/install/package/anagrams.zip"
                },
                "type": "library",
                "autoload": {
                    "classmap": [
                        "anagram.php"
                    ]
                }
            }
        ]
    }
}
