{
    "packages": {
        "phpclasses/dddreveal": [
            {
                "name": "phpclasses/dddreveal",
                "version": "1.0.3",
                "version_normalized": "1.0.3.0",
                "dist": {
                    "type": "zip",
                    "url": "https://www.phpclasses.org/install/package/dddreveal.zip"
                },
                "require": {
                    "laudirbispo/classname": "1.2.*",
                    "php": "^7.4",
                    "phpclasses/classname": "1.2.1"
                },
                "type": "library",
                "autoload": {
                    "psr-4": {
                        "laudirbispo\\DDDReveal\\": "src"
                    }
                }
            }
        ]
    }
}
