{
    "packages": {
        "phpclasses/dip": [
            {
                "name": "phpclasses/dip",
                "version": "0.0.1",
                "version_normalized": "0.0.1.0",
                "dist": {
                    "type": "zip",
                    "url": "https://www.phpclasses.org/install/package/dip.zip"
                },
                "type": "library",
                "autoload": {
                    "classmap": [
                        "CORE/Dip.action.class.php",
                        "CORE/Dip.class.php"
                    ]
                }
            }
        ]
    }
}
