{
    "packages": {
        "phpclasses/easy_acl": [
            {
                "name": "phpclasses/easy_acl",
                "version": "1.0",
                "version_normalized": "1.0.0.0",
                "dist": {
                    "type": "zip",
                    "url": "https://www.phpclasses.org/install/package/easy_acl.zip"
                },
                "type": "library",
                "autoload": {
                    "classmap": [
                        "easy_acl.php"
                    ]
                }
            }
        ]
    }
}
