{
    "packages": {
        "phpclasses/loglimiter": [
            {
                "name": "phpclasses/loglimiter",
                "version": "0.3",
                "version_normalized": "0.3.0.0",
                "dist": {
                    "type": "zip",
                    "url": "https://www.phpclasses.org/install/package/loglimiter.zip"
                },
                "type": "library",
                "autoload": {
                    "classmap": [
                        "loglimiter.class.php"
                    ]
                }
            }
        ]
    }
}
