{
    "packages": {
        "phpclasses/mysqlwithelasticsear": [
            {
                "name": "phpclasses/mysqlwithelasticsear",
                "version": "8",
                "version_normalized": "8.0.0.0",
                "dist": {
                    "type": "zip",
                    "url": "https://www.phpclasses.org/install/package/mysqlwithelasticsear.zip"
                },
                "require": {
                    "elasticsearch/elasticsearch": ">=2",
                    "phpunit/phpunit": "5.*"
                },
                "type": "library",
                "autoload": {
                    "psr-4": {
                        "SearchElastic\\": "src/SearchElastic/",
                        "ElasticSearchClient\\": "src/ElasticSearchClient/",
                        "SyncMySql\\": "src/SyncMySql/",
                        "MySQLWithElasticsearchExceptions\\": "src/MySQLWithElasticsearchExceptions/"
                    }
                }
            }
        ]
    }
}
