{
    "packages": {
        "phpclasses/mysurvey": [
            {
                "name": "phpclasses/mysurvey",
                "version": "1.0.0",
                "version_normalized": "1.0.0.0",
                "dist": {
                    "type": "zip",
                    "url": "https://www.phpclasses.org/install/package/mysurvey.zip"
                },
                "type": "library",
                "autoload": {
                    "classmap": [
                        "encuesta.inc.php",
                        "controler.encuestas.php"
                    ]
                }
            }
        ]
    }
}
