{
    "packages": {
        "phpclasses/ontimecore": [
            {
                "name": "phpclasses/ontimecore",
                "version": "3.51",
                "version_normalized": "3.51.0.0",
                "dist": {
                    "type": "zip",
                    "url": "https://www.phpclasses.org/install/package/ontimecore.zip"
                },
                "type": "library",
                "autoload": {
                    "classmap": [
                        "OTicore.php",
                        "OnTime.php",
                        "OnTimeContent.php",
                        "OnTimeCoreA.php",
                        "OnTimeCoreB.php",
                        "OnTimeCripto.php",
                        "OnTimeDebug.php",
                        "OnTimeFunctions.php",
                        "OnTimeAllways.php",
                        "OnTimetmp.php",
                        "OnTimeAllways.php",
                        "OnTimetmp.php"
                    ]
                }
            }
        ]
    }
}
