{
    "packages": {
        "phpclasses/parsecompile": [
            {
                "name": "phpclasses/parsecompile",
                "version": "0.3",
                "version_normalized": "0.3.0.0",
                "dist": {
                    "type": "zip",
                    "url": "https://www.phpclasses.org/install/package/parsecompile.zip"
                },
                "type": "library",
                "autoload": {
                    "classmap": [
                        "Sql_Compiler/Sql_CompilerInsert.class.php",
                        "Sql_Compiler/Sql_CompilerReplace.class.php",
                        "Sql_Compiler/Sql_CompilerSelect.class.php",
                        "Sql_Compiler/Sql_CompilerUpdate.class.php",
                        "Sql_Compiler/Sql_CompilerDelete.class.php",
                        "Sql_Compiler/Sql_CompilerFlow.class.php",
                        "Sql_Compiler/Sql_CompilerFunction.class.php",
                        "Sql_Interface/Sql_InterfaceCompiler.class.php",
                        "Sql_Interface/Sql_InterfaceParser.class.php",
                        "Sql_Parser/Sql_ParserDelete.class.php",
                        "Sql_Parser/Sql_ParserFlow.class.php",
                        "Sql_Parser/Sql_ParserFunction.class.php",
                        "Sql_Parser/Sql_ParserInsert.class.php",
                        "Sql_Parser/Sql_ParserReplace.class.php",
                        "Sql_Parser/Sql_ParserSelect.class.php",
                        "Sql_Parser/Sql_ParserUpdate.class.php",
                        "Sql_Lexer.class.php",
                        "Sql_Object.class.php",
                        "Sql_Compiler.class.php",
                        "Sql_Parser.class.php",
                        "Sql.class.php",
                        "Sql_Compiler/Sql_CompilerUnion.class.php",
                        "Sql_Parser/Sql_ParserUnion.class.php"
                    ]
                }
            }
        ]
    }
}
