{
    "packages": {
        "phpclasses/pdo-model": [
            {
                "name": "phpclasses/pdo-model",
                "version": "1.0.0",
                "version_normalized": "1.0.0.0",
                "dist": {
                    "type": "zip",
                    "url": "https://www.phpclasses.org/install/package/pdo-model.zip"
                },
                "type": "library",
                "autoload": {
                    "classmap": [
                        "DBAbstract.php",
                        "ModelAbstract.php",
                        "Sysconf.php"
                    ]
                }
            }
        ]
    }
}
