{
    "packages": {
        "phpclasses/phm": [
            {
                "name": "phpclasses/phm",
                "version": "1.4",
                "version_normalized": "1.4.0.0",
                "dist": {
                    "type": "zip",
                    "url": "https://www.phpclasses.org/install/package/phm.zip"
                },
                "type": "library",
                "autoload": {
                    "classmap": [
                        "msg.cls.php"
                    ]
                }
            }
        ]
    }
}
