{
    "packages": {
        "phpclasses/secure-file": [
            {
                "name": "phpclasses/secure-file",
                "version": "1.0",
                "version_normalized": "1.0.0.0",
                "dist": {
                    "type": "zip",
                    "url": "https://www.phpclasses.org/install/package/secure-file.zip"
                },
                "type": "library",
                "autoload": {
                    "classmap": [
                        "SecureFile.class.php"
                    ]
                }
            }
        ]
    }
}
