{
    "packages": {
        "phpclasses/sql-koruma": [
            {
                "name": "phpclasses/sql-koruma",
                "version": "3.2",
                "version_normalized": "3.2.0.0",
                "dist": {
                    "type": "zip",
                    "url": "https://www.phpclasses.org/install/package/sql-koruma.zip"
                },
                "type": "library",
                "autoload": {
                    "classmap": [
                        "sqlkoruma.php"
                    ]
                }
            }
        ]
    }
}
